shimexpy_cli/__init__.py
shimexpy_cli/angles_correction.py
shimexpy_cli/cli.py
shimexpy_cli/config.py
shimexpy_cli/correcting_stripes.py
shimexpy_cli/corrections.py
shimexpy_cli/crop.py
shimexpy_cli/directories.py
shimexpy_cli/exceptions.py
shimexpy_cli/execute.py
shimexpy_cli/logging.py
shimexpy_cli/processor.py
shimexpy_cli-0.1.0.dist-info/METADATA
shimexpy_cli-0.1.0.dist-info/WHEEL
shimexpy_cli-0.1.0.dist-info/entry_points.txt
shimexpy_cli-0.1.0.dist-info/top_level.txt
shimexpy_cli-0.1.0.dist-info/RECORD
