Metadata-Version: 2.4
Name: shimexpy_cli
Version: 0.1.0
Summary: Command Line Interface for Shimexpy - Spatial Harmonics Imaging
Author: Jorge Luis Beltran Diaz
License: Apache-2.0
Classifier: Intended Audience :: Science/Research
Classifier: License :: OSI Approved :: Apache Software License
Classifier: Programming Language :: Python :: 3.9
Classifier: Operating System :: POSIX :: Linux
Requires-Python: >=3.7
Requires-Dist: shimexpy-core>=0.1.0
